shadowcopy/__init__.py
shadowcopy/exceptions.py
shadowcopy/shadow.py
shadowcopy-0.0.4.dist-info/LICENSE.md
shadowcopy-0.0.4.dist-info/METADATA
shadowcopy-0.0.4.dist-info/WHEEL
shadowcopy-0.0.4.dist-info/top_level.txt
shadowcopy-0.0.4.dist-info/RECORD
