Metadata-Version: 2.1
Name: shadowcopy
Version: 0.0.4
Summary: A project for shadowcopy
Author-email: csm10495 <csm10495@gmail.com>
License: MIT License
Project-URL: homepage, https://github.com/csm10495/shadowcopy
Project-URL: repository, https://github.com/csm10495/shadowcopy
Project-URL: documentation, https://csm10495.github.io/shadowcopy
Classifier: Intended Audience :: Developers
Classifier: Natural Language :: English
Classifier: Operating System :: Microsoft :: Windows
Classifier: Programming Language :: Python
Classifier: Programming Language :: Python :: 3
Requires-Python: >=3.7
License-File: LICENSE.md
